CHANGES.txt
COPYRIGHT.txt
LICENSE.txt
README.txt
bootstrap.py
buildout.cfg
setup.py
src/zope/__init__.py
src/zope.documenttemplate.egg-info/PKG-INFO
src/zope.documenttemplate.egg-info/SOURCES.txt
src/zope.documenttemplate.egg-info/dependency_links.txt
src/zope.documenttemplate.egg-info/namespace_packages.txt
src/zope.documenttemplate.egg-info/not-zip-safe
src/zope.documenttemplate.egg-info/requires.txt
src/zope.documenttemplate.egg-info/top_level.txt
src/zope/documenttemplate/__init__.py
src/zope/documenttemplate/documenttemplate.py
src/zope/documenttemplate/dt_html.py
src/zope/documenttemplate/dt_if.py
src/zope/documenttemplate/dt_in.py
src/zope/documenttemplate/dt_insv.py
src/zope/documenttemplate/dt_let.py
src/zope/documenttemplate/dt_raise.py
src/zope/documenttemplate/dt_return.py
src/zope/documenttemplate/dt_string.py
src/zope/documenttemplate/dt_try.py
src/zope/documenttemplate/dt_util.py
src/zope/documenttemplate/dt_var.py
src/zope/documenttemplate/dt_with.py
src/zope/documenttemplate/pdocumenttemplate.py
src/zope/documenttemplate/ustr.py
src/zope/documenttemplate/tests/__init__.py
src/zope/documenttemplate/tests/dtmltestbase.py
src/zope/documenttemplate/tests/testdt_if.py
src/zope/documenttemplate/tests/testdt_in.py
src/zope/documenttemplate/tests/testdt_try.py
src/zope/documenttemplate/tests/testdt_var.py
src/zope/documenttemplate/tests/testdt_with.py
src/zope/documenttemplate/tests/testustr.py
src/zope/documenttemplate/untrusted/README.txt
src/zope/documenttemplate/untrusted/__init__.py
src/zope/documenttemplate/untrusted/tests.py
src/zope/documenttemplate/untrusted/untrusted.py